vi/__init__.py
vi/check_config.py
vi/config.yaml
vi/init_gs.py
vi/main.py
vi/opts.py
vi/version.py
vi/vi.conf
vi/api/__init__.py
vi/api/app.wsgi
vi/api/rest.py
vi/cmd/__init__.py
vi/cmd/labkit.py
vi/cmd/labkit_manage.py
vi/databank/__init__.py
vi/ensemble/__init__.py
vi/ensemble/base.py
vi/ensemble/conformerdb.py
vi/ensemble/folder.py
vi/ensemble/listensemble.py
vi/ensemble/listensemble_bak.py
vi/ensemble_mongo/__init__.py
vi/ensemble_mongo/converge.py
vi/ensemble_mongo/cut.py
vi/ensemble_mongo/ensemble.py
vi/ensemble_mongo/fit.py
vi/ensemble_mongo/merge.py
vi/interpreter/__init__.py
vi/interpreter/context.py
vi/interpreter/dealwithline.py
vi/interpreter/hello.yml
vi/interpreter/loaders.py
vi/interpreter/pkgs.py
vi/interpreter/runner.py
vi/interpreter/origin/1.xyz
vi/module_settings/compute.gaussian.yml
vi/module_settings/conformer.conformer.yml
vi/module_settings/ensemble.yml
vi/module_settings/esemble.cut.yml
vi/module_settings/esemble.merge.yml
vi/module_settings/sample.ga.yml
vi/module_settings/sample.generate.yml
vi/parallel/__init__.py
vi/parallel/mapreduce_ensemble.py
vi/parallel/mapreduce_file.py
vi/scheduler/__init__.py
vi/scheduler/out_ref_test.py
vi/scheduler/push.py
vi/scheduler/worker.py
vi/tests/__init__.py
vi/tests/unit/__init__.py
vi/tests/unit/test_check_config.py
vi/tests/unit/test_config.py
vi/tests/unit/test_init_gs.py
vi/tests/unit/test_main.py
vi/tests/unit/test_opts.py
vi/tests/unit/test_version.py
vi/tests/unit/algorithm/test_base.py
vi/tests/unit/algorithm/aga/test_labaga.py
vi/tests/unit/algorithm/fit/test_forcebalancefit.py
vi/tests/unit/algorithm/ga/test_cga.py
vi/tests/unit/algorithm/ga/test_individual.py
vi/tests/unit/algorithm/sys/test_sys.py
vi/tests/unit/api/test_rest.py
vi/tests/unit/api/rq_dashboard/test_cli.py
vi/tests/unit/api/rq_dashboard/test_default_settings.py
vi/tests/unit/api/rq_dashboard/test_version.py
vi/tests/unit/api/rq_dashboard/test_web.py
vi/tests/unit/cmd/test_cli.py
vi/tests/unit/cmd/test_cli_inside.py
vi-0.9.dist-info/licenses/AUTHORS
vi-0.9.dist-info/METADATA
vi-0.9.dist-info/WHEEL
vi-0.9.dist-info/entry_points.txt
vi-0.9.dist-info/pbr.json
vi-0.9.dist-info/top_level.txt
vi-0.9.dist-info/RECORD
