Metadata-Version: 2.4
Name: vi
Version: 0.9
Summary: Vector Interpreter - computational toolkit for biophysical design platforms
Home-page: https://github.com/lhrkkk/vi.git
Author: lhr
Author-email: lhr <airhenry@gmail.com>
License: GPL-2.0
Project-URL: Homepage, https://github.com/lhrkkk/vi.git
Project-URL: Repository, https://github.com/lhrkkk/vi.git
Project-URL: Issues, https://github.com/lhrkkk/vi/issues
Keywords: molecular,simulation,chemistry,computational
Classifier: Development Status :: 3 - Alpha
Classifier: Environment :: Console
Classifier: Intended Audience :: Developers
Classifier: Intended Audience :: Education
Classifier: Intended Audience :: Science/Research
Classifier: License :: OSI Approved :: GNU General Public License v2 (GPLv2)
Classifier: Operating System :: POSIX :: Linux
Classifier: Programming Language :: Python
Classifier: Programming Language :: Python :: 2.7
Classifier: Programming Language :: Python :: 3
Classifier: Programming Language :: Python :: 3.6
Classifier: Programming Language :: Python :: 3.7
Classifier: Programming Language :: Python :: 3.8
Classifier: Programming Language :: Python :: 3.9
Classifier: Programming Language :: Python :: 3.10
Classifier: Programming Language :: Python :: 3.11
Classifier: Programming Language :: Python :: 3.12
Classifier: Topic :: Scientific/Engineering :: Chemistry
Classifier: Topic :: Scientific/Engineering :: Physics
Requires-Python: !=3.0.*,!=3.1.*,!=3.2.*,!=3.3.*,!=3.4.*,!=3.5.*,>=2.7
License-File: AUTHORS
Requires-Dist: six>=1.10.0
Requires-Dist: pbr>=2.0.0
Dynamic: author
Dynamic: home-page
Dynamic: license-file
